pandas_gpt/__init__.py
pandas_gpt/completers/__init__.py
pandas_gpt/completers/litellm.py
pandas_gpt/completers/openai.py
pandas_gpt/completers/openrouter.py
pandas_gpt-1.0.0.dist-info/LICENSE
pandas_gpt-1.0.0.dist-info/METADATA
pandas_gpt-1.0.0.dist-info/WHEEL
pandas_gpt-1.0.0.dist-info/top_level.txt
pandas_gpt-1.0.0.dist-info/RECORD
