Metadata-Version: 2.1
Name: pandas-gpt
Version: 1.0.0
Summary: Power up your data science workflow with ChatGPT
Author: Ryan Vandersmith
Requires-Python: >=3.10
License-File: LICENSE
Requires-Dist: pandas
Provides-Extra: openai
Requires-Dist: openai; extra == "openai"
Provides-Extra: litellm
Requires-Dist: litellm; extra == "litellm"
